rePLS/__init__.py
rePLS/residual_regression.py
rePLS-0.0.5.dist-info/LICENSE
rePLS-0.0.5.dist-info/METADATA
rePLS-0.0.5.dist-info/WHEEL
rePLS-0.0.5.dist-info/top_level.txt
rePLS-0.0.5.dist-info/RECORD
