Metadata-Version: 2.1
Name: rePLS
Version: 0.0.5
Summary: Residual Partial Least Squares Learning 
Author: thanhvd
Author-email: duythanhvu.uet@gmail.com
Keywords: PLS,rePLS,PCR,LR
License-File: LICENSE
Requires-Dist: numpy
Requires-Dist: scikit-learn
